eventdispatch/__init__.py
eventdispatch/common1.py
eventdispatch/composite_semaphore.py
eventdispatch/core.py
eventdispatch/example1.py
eventdispatch/example2.py
eventdispatch-0.2.25.dist-info/licenses/LICENSE
eventdispatch-0.2.25.dist-info/licenses/NOTICE
eventdispatch-0.2.25.dist-info/METADATA
eventdispatch-0.2.25.dist-info/WHEEL
eventdispatch-0.2.25.dist-info/entry_points.txt
eventdispatch-0.2.25.dist-info/top_level.txt
eventdispatch-0.2.25.dist-info/RECORD
