Metadata-Version: 2.4
Name: eventdispatch
Version: 0.2.25
Summary: Event Dispatch: discrete time synchronization
Home-page: http://github.com/cyan-at/python-eventdispatch
Author: Charlie Yan
Author-email: Charlie Yan <cyanatg@gmail.com>
License: 
Project-URL: Homepage, https://github.com/cyan-at/python-eventdispatch
Project-URL: Issues, https://github.com/cyan-at/python-eventdispatch/issues
Keywords: threading,eventdispatch,event,dispatch,concurrency,synchronization,robotics,behaviour,behavior,behaviortree
Classifier: Programming Language :: Python :: 3
Classifier: Operating System :: POSIX :: Linux
Requires-Python: >=3.9
License-File: LICENSE
License-File: NOTICE
Requires-Dist: argparse
Dynamic: author
Dynamic: home-page
Dynamic: license-file
